ai_common/__init__.py
ai_common/model_loader.py
ai_common/utils.py
ai_common/exception/__init__.py
ai_common/exception/custom_exception.py
ai_common/logger/__init__.py
ai_common/logger/custom_logger.py
ai_common/logger/logger_utils.py
ai_common/prompts/__init__.py
ai_common/prompts/generic_prompts.py
nishkoder_ai_common-0.1.5.dist-info/licenses/LICENSE
nishkoder_ai_common-0.1.5.dist-info/METADATA
nishkoder_ai_common-0.1.5.dist-info/WHEEL
nishkoder_ai_common-0.1.5.dist-info/top_level.txt
nishkoder_ai_common-0.1.5.dist-info/RECORD
